tornado_ping/__init__.py
tornado_ping-0.3.6.dist-info/METADATA
tornado_ping-0.3.6.dist-info/WHEEL
tornado_ping-0.3.6.dist-info/top_level.txt
tornado_ping-0.3.6.dist-info/RECORD
